{"cameraMode":{"drawMode":0,"name":"Shaded","section":"Shading Mode"},"sceneLighting":false,"audioPlay":false,"sceneViewState":{"showFog":true,"showMaterialUpdate":false,"showSkybox":false,"showFlares":true,"showImageEffects":true,"showParticleSystems":true},"in2DMode":false,"pivot":{"x":3.2382049560546877,"y":0.8587331771850586,"z":-15.64450740814209},"rotation":{"x":0.000951061665546149,"y":-0.9575228691101074,"z":0.2883457839488983,"w":0.003156122984364629},"size":0.5385569334030151,"orthographic":false}